{"event": "2025mshsl", "info": {"name": "Custom Event", "year": 2025}, "teams": [{"team_number": 3276, "nickname": "TOOLCATS"}, {"team_number": 4607, "nickname": "C.I.S."}, {"team_number": 6147, "nickname": "Tonkabots"}, {"team_number": 2530, "nickname": "Inconceivable"}, {"team_number": 5913, "nickname": "Patriotics"}, {"team_number": 2847, "nickname": "The MegaHertz"}, {"team_number": 4728, "nickname": "ROCORI Ratcheteers"}, {"team_number": 2129, "nickname": "Ultraviolet"}, {"team_number": 2052, "nickname": "KnightKrawler"}, {"team_number": 7257, "nickname": "Semiconductors"}, {"team_number": 2491, "nickname": "NoMythic"}, {"team_number": 7028, "nickname": "Binary Battalion"}, {"team_number": 3297, "nickname": "Full Metal Jackets"}, {"team_number": 3313, "nickname": "Mechatronics"}, {"team_number": 6045, "nickname": "Sabre Robotics"}, {"team_number": 3130, "nickname": "The ERRORs"}, {"team_number": 9576, "nickname": "Loretto Lightning"}, {"team_number": 3100, "nickname": "Lightning Turtles"}, {"team_number": 5653, "nickname": "Iron Mosquitos"}, {"team_number": 4009, "nickname": "Duluth DNA Robotics"}, {"team_number": 5348, "nickname": "Charger Robotics"}, {"team_number": 2883, "nickname": "F.R.E.D (FIRST Robotics Eng..."}, {"team_number": 2987, "nickname": "Rogue Robotics"}, {"team_number": 3082, "nickname": "Chicken Bot Pie"}, {"team_number": 6146, "nickname": "Blackjacks"}, {"team_number": 3883, "nickname": "Data Bits"}, {"team_number": 7541, "nickname": "Maple River Robotics"}, {"team_number": 2472, "nickname": "Centurions"}, {"team_number": 2470, "nickname": "Team BJORG"}, {"team_number": 3102, "nickname": "Tech-No-Tigers"}, {"team_number": 3058, "nickname": "ANNDROIDS"}, {"team_number": 2480, "nickname": "Iron Paws"}, {"team_number": 6749, "nickname": "tERAbytes"}, {"team_number": 6132, "nickname": "Iron Rangers"}, {"team_number": 2225, "nickname": "Rebel Robotics"}, {"team_number": 7530, "nickname": "Raiders of the Lost Spark"}], "scouters": ["[Core Scouting] Michael", "[Core Scouting] James Hanstedt", "[Drive Coach] Yoonju", "[Student] Aditi", "[Student] Alex", "[Student] Andrew", "[Student] Caleb", "[Student] Carly Thompson", "[Student] Cassius", "[Student] Catherine", "[Student] Clayton", "[Student] Craig", "[Student] Dana", "[Student] Dylan", "[Student] Eric", "[Student] Henry", "[Student] Hunter", "[Student] Jackson", "[Student] Jacque", "[Student] James Hendrickson", "[Student] Jay", "[Student] Kai", "[Student] Kylee", "[Student] Lorelei", "[Student] Matilde", "[Student] Nia", "[Student] Pranya", "[Student] Quinn", "[Student] Ransom", "[Student] Sarah", "[Student] Simon", "[Student] Sophie", "[Student] Sunghwan", "[Student] Xiaoyan", "[Student] Zack", "[Drive team] Luke Luke Luke", "[Drive team] Arden Amogus Peng", "[Drive team] Finley octavious the third", "[Drive team] Julia Bumpers Logelin", "[Alumni] Colton", "[Mentor] Micah", "[Mentor] Aaron", "[Mentor] Nicole", "[Mentor] Jen", "[Mentor] Kari", "[Mentor] Stacy", "[Mentor] Mroz", "[Mentor] Nick", "[Mentor] Dr.B", "[Mentor] Jeff", "[Mentor] Pranay", "[Coach] Aaron", "[Coach] Tim", "[Coach] Amanda", "[Coach] Yi", "[Family] Alan", "[Family] Aaron M"]}
